collective.easyform-4.4.0-py3.13-nspkg.pth
collective/easyform/Form.gif
collective/easyform/__init__.py
collective/easyform/actions.py
collective/easyform/actions.zcml
collective/easyform/api.py
collective/easyform/config.py
collective/easyform/configure.zcml
collective/easyform/content.py
collective/easyform/exportimport.py
collective/easyform/exportimport.zcml
collective/easyform/fields.py
collective/easyform/fields.zcml
collective/easyform/permissions.zcml
collective/easyform/serializer.py
collective/easyform/setuphandlers.py
collective/easyform/subscribers.py
collective/easyform/subscribers.zcml
collective/easyform/validators.py
collective/easyform/validators.zcml
collective/easyform/vocabularies.py
collective/easyform/vocabularies.zcml
collective/easyform/browser/__init__.py
collective/easyform/browser/action_input.pt
collective/easyform/browser/actions.py
collective/easyform/browser/actions.zcml
collective/easyform/browser/actions_listing.pt
collective/easyform/browser/configure.zcml
collective/easyform/browser/controlpanel.py
collective/easyform/browser/easyform.css
collective/easyform/browser/easyform_form.pt
collective/easyform/browser/easyform_form_embedded.pt
collective/easyform/browser/easyform_layout.pt
collective/easyform/browser/empty.pt
collective/easyform/browser/exportimport.py
collective/easyform/browser/fields.py
collective/easyform/browser/fields.zcml
collective/easyform/browser/fields_listing.pt
collective/easyform/browser/label.pt
collective/easyform/browser/likert.py
collective/easyform/browser/likert.zcml
collective/easyform/browser/likert_display.pt
collective/easyform/browser/likert_hidden.pt
collective/easyform/browser/likert_input.pt
collective/easyform/browser/model_listing.pt
collective/easyform/browser/modeleditor.pt
collective/easyform/browser/rich_label.pt
collective/easyform/browser/saveddata.pt
collective/easyform/browser/saveddata_form.pt
collective/easyform/browser/thank_you.pt
collective/easyform/browser/view.py
collective_easyform-4.4.0.dist-info/METADATA
collective_easyform-4.4.0.dist-info/WHEEL
collective_easyform-4.4.0.dist-info/entry_points.txt
collective_easyform-4.4.0.dist-info/namespace_packages.txt
collective_easyform-4.4.0.dist-info/top_level.txt
collective_easyform-4.4.0.dist-info/RECORD
