Metadata-Version: 2.4
Name: collective.easyform
Version: 4.4.0
Summary: Forms for Plone
Home-page: https://github.com/collective/collective.easyform
Author: Roman Kozlovskyi
Author-email: krzroman@gmail.com
Maintainer: Plone Release Team
Maintainer-email: releaseteam@plone.org
License: GPLv2
Keywords: form plone ttw builder email
Classifier: Development Status :: 5 - Production/Stable
Classifier: Environment :: Web Environment
Classifier: Framework :: Plone
Classifier: Framework :: Plone :: Addon
Classifier: Framework :: Plone :: 6.0
Classifier: Framework :: Plone :: 6.1
Classifier: Programming Language :: Python
Classifier: Programming Language :: Python :: 3.9
Classifier: Programming Language :: Python :: 3.10
Classifier: Programming Language :: Python :: 3.11
Classifier: Programming Language :: Python :: 3.12
Classifier: Programming Language :: Python :: 3.13
Classifier: Operating System :: OS Independent
Classifier: License :: OSI Approved :: GNU General Public License v2 (GPLv2)
Requires-Python: >=3.9
Requires-Dist: plone.api
Requires-Dist: plone.app.dexterity
Requires-Dist: plone.app.textfield>=1.2.8
Requires-Dist: plone.autoform
Requires-Dist: plone.dexterity
Requires-Dist: plone.namedfile
Requires-Dist: plone.schema
Requires-Dist: plone.schemaeditor>=4.0.0b1
Requires-Dist: plone.supermodel
Requires-Dist: plone.restapi
Requires-Dist: Products.CMFPlone>=6.0.0b1
Requires-Dist: Products.validation>=3.0.0
Requires-Dist: setuptools
Requires-Dist: six
Provides-Extra: downloadxlsx
Requires-Dist: openpyxl; extra == "downloadxlsx"
Provides-Extra: recaptcha
Requires-Dist: plone.formwidget.recaptcha; extra == "recaptcha"
Provides-Extra: hcaptcha
Requires-Dist: plone.formwidget.hcaptcha; extra == "hcaptcha"
Provides-Extra: norobots
Requires-Dist: collective.z3cform.norobots; extra == "norobots"
Provides-Extra: ploneformgen
Requires-Dist: Products.PloneFormGen; extra == "ploneformgen"
Provides-Extra: test
Requires-Dist: beautifulsoup4; extra == "test"
Requires-Dist: plone.app.testing[robot]; extra == "test"
Requires-Dist: plone.app.robotframework; extra == "test"
Requires-Dist: plone.app.contenttypes; extra == "test"
Requires-Dist: plone.formwidget.recaptcha; extra == "test"
Requires-Dist: plone.formwidget.hcaptcha; extra == "test"
Requires-Dist: robotframework-selenium2library; extra == "test"
Requires-Dist: robotframework-selenium2screenshots; extra == "test"
Dynamic: author
Dynamic: author-email
Dynamic: classifier
Dynamic: description
Dynamic: home-page
Dynamic: keywords
Dynamic: license
Dynamic: maintainer
Dynamic: maintainer-email
Dynamic: provides-extra
Dynamic: requires-dist
Dynamic: requires-python
Dynamic: summary
